vatsim/__init__.py
vatsim/constants.py
vatsim/fetchers.py
vatsim/py.typed
vatsim/types.py
vatsim-0.2.0.dist-info/METADATA
vatsim-0.2.0.dist-info/WHEEL
vatsim-0.2.0.dist-info/licenses/LICENSE
vatsim-0.2.0.dist-info/RECORD
