Metadata-Version: 2.3
Name: vatsim
Version: 0.2.0
Summary: Library for interacting with VATSIM APIs and data
Author-email: Franz Pletz <fpletz@fnordicwalking.de>, Alex Legler <alex@a3li.li>, Robin Gloster <mail@glob.in>
License: MIT License
Classifier: Development Status :: 3 - Alpha
Classifier: Intended Audience :: Developers
Classifier: License :: OSI Approved :: MIT License
Classifier: Operating System :: OS Independent
Classifier: Programming Language :: Python :: 3
Classifier: Topic :: Games/Entertainment :: Simulation
Classifier: Topic :: Software Development :: Libraries :: Python Modules
Requires-Python: >=3.10
Requires-Dist: pydantic>=2.10.2
Requires-Dist: regex>=2024.11.6
Requires-Dist: requests>=2.32.3
